<?xml version="1.0" encoding="utf-8"?>
<crawler><fetch>true</fetch><url>http://gitam.edu/hostels</url><domain>gitam.edu</domain><path></path><links count="75"><link>www.gitam.edu</link><link>www.gitam.edu/campus/hyderabad-campus</link><link>www.gitam.edu/campus/bengaluru-campus</link><link>webmail.gitam.edu/</link><link>gitam.edu/media/pro</link><link>gitam.edu/about/career</link><link>krc.gitam.edu</link><link>gitam.edu/maps</link><link>alumni.gitam.edu</link><link>gitamstudent.gitam.edu/PARENT/Login.aspx</link><link>gitam.edu/directory/people</link><link>cdl.gitam.edu</link><link>login.gitam.edu/gitamsignon</link><link>www.gitam.edu/</link><link>gitam.edu/about/gitam-at-glance</link><link>gitam.edu/about/president</link><link>gitam.edu/about/chancellor</link><link>gitam.edu/about/vice-chancellor</link><link>gitam.edu/about/pro-vice-chancellor-vsp</link><link>gitam.edu/about/pro-vice-chancellor-hyd</link><link>gitam.edu/about/pro-vice-chancellor-blr</link><link>gitam.edu/admissions</link><link>gitam.edu/admissions/engineering/undergraduate-programs</link><link>gitam.edu/admissions/science/undergraduate-programs</link><link>gitam.edu/admissions/management/undergraduate-programs</link><link>gitam.edu/admissions/pharmacy/undergraduate-programs</link><link>gitam.edu/admissions/architecture/undergraduate-programs</link><link>gitam.edu/admissions/law/undergraduate-programs</link><link>gitam.edu/admissions/medical/mbbs-programs</link><link>gitam.edu/admissions/nursing/nursing-programs</link><link>gitam.edu/academics/Campuses</link><link>gitam.edu/evaluation/doe-administration</link><link>gitam.edu/academics/academic-calendar</link><link>gitam.edu/academics/academic-affairs</link><link>gitam.edu/research/research-centers</link><link>gitam.edu/research/central-research-laboratory</link><link>gitam.edu/research/advanced-research-labs</link><link>gitam.edu/research/sponsored-research</link><link>gitam.edu/industry/collaborative-academic-programs</link><link>gitam.edu/industry/collaborative-research</link><link>gitam.edu/industry/internships</link><link>gitam.edu/industry/consultancy</link><link>gitam.edu/industry/management-development-programs</link><link>gitam.edu/industry/adjunct-faculty</link><link>gitam.edu/industry/Outreach-MOUs</link><link>gitam.edu/industry/CEO-lecture-series</link><link>gitam.edu/placements/achievers-day</link><link>gitam.edu/placements/training-placement-centre</link><link>gitam.edu/placements/prominent-recruiter</link><link>gitam.edu/in-campus/student-chapters</link><link>gitam.edu/in-campus/student-clubs</link><link>gitam.edu/hostels</link><link>gitam.edu/in-campus/student-fests</link><link>gitam.edu/athletics</link><link>gitam.edu/in-campus/amenities</link><link>gitam.edu/in-campus/campus-connectivity</link><link>gitam.edu/contact-us</link><link>gitam.edu/Student-housing</link><link>gitam.edu/in-campus/auditoriums</link><link>gitam.edu/in-campus/dining</link><link>gitam.edu/in-campus/safety-and-security</link><link>gitam.edu/in-campus/health-and-wellness</link><link>gitam.edu/in-campus/spirituality</link><link>gitam.edu/in-campus/bus-service</link><link>gitam.edu/in-campus/sustainability</link><link>gitam.edu/in-campus/gandhi-museum-at-sarvodaya-soudha</link><link>gitam.edu/in-campus/prevention-of-caste-based-discrimination</link><link>gitam.edu/</link><link>gitam.edu/ipi</link><link>iqac.gitam.edu/NIRF2017.aspx</link><link>www.gitam.edu/evaluation/doe-administration</link><link>www.gitam.edu/placements/training-placement-centre</link><link>www.gitam.edu/placements/prominent-recruiter</link><link>doeresults.gitam.edu/onlineresults/pages/Newgrdcrdinput1.aspx</link><link>www.gitam.edu/in-campus/student-chapters</link></links><out count="24"/><title>Student housing</title><words count="183"><word count="2">student</word><word count="1">housingcampuses</word><word count="1">visakhapatnamhyderabadbengaluruwebmailmediacareerslibrarymapsalumniparentsdirectorycdlmy.gitamstudent</word><word count="1">housingmenu</word><word count="2">about</word><word count="2">us</word><word count="3">gitam</word><word count="1">at</word><word count="2">a</word><word count="1">glancepresident</word><word count="1">chancellor</word><word count="1">vice-chancellor</word><word count="3">pro</word><word count="3">vc</word><word count="4">-</word><word count="1">vsp</word><word count="1">hyd</word><word count="1">blr</word><word count="1">more...admissionsengineeringsciencemanagementgsibpharmacyarchitecturelawmedicalnursingacademicsgitam</word><word count="1">campuses</word><word count="1">evaluationlibraryacademic</word><word count="1">calendaracademic</word><word count="1">affairs</word><word count="5">research</word><word count="2">centres</word><word count="1">central</word><word count="1">advanced</word><word count="1">sponsored</word><word count="1">researchcollaborations</word><word count="1">collaborative</word><word count="1">internship</word><word count="1">consultancy</word><word count="1">mdp%27s</word><word count="1">adjunct</word><word count="1">faculty</word><word count="1">outreach</word><word count="1">ceo</word><word count="1">lecture</word><word count="1">more...</word><word count="1">placements</word><word count="1">placement</word><word count="1">achievers</word><word count="1">dayprominent</word><word count="1">recruiterin</word><word count="3">campus</word><word count="2">chaptersstudent</word><word count="2">clubsstudent</word><word count="1">housingstudent</word><word count="1">festsathleticsamenitiescampus</word><word count="1">connectivity</word><word count="1">more...contact</word><word count="1">ustoggle</word><word count="1">navigationstudent</word><word count="1">festsstudent</word><word count="1">housingauditoriumsathleticsdiningamenitiessafety</word><word count="15">and</word><word count="1">securitycampus</word><word count="1">connectivityhealth</word><word count="1">wellnessspiritualitybus</word><word count="1">servicesustainabilitygandhi</word><word count="1">museumcaste</word><word count="1">discriminationvisakhapatnam</word><word count="1">campushyderabad</word><word count="1">campusbengaluru</word><word count="3">boys</word><word count="6">hostel</word><word count="1">saddarma</word><word count="9">sadanhostel</word><word count="13">timingsbreakfast</word><word count="18">7.30</word><word count="13">am</word><word count="52">to</word><word count="22">9.00</word><word count="13">amlunch</word><word count="9">12.00</word><word count="39">pm</word><word count="9">2.00</word><word count="13">pmsnacks</word><word count="9">4.30</word><word count="13">6.00</word><word count="13">pmdinner</word><word count="13">pmfacilitieseco-friendly</word><word count="13">environmentwifisteam</word><word count="13">cookingsafe</word><word count="13">drinking</word><word count="13">waterround</word><word count="13">the</word><word count="13">clock</word><word count="13">securityavailability</word><word count="13">of</word><word count="13">qualified</word><word count="13">doctors</word><word count="39">resident</word><word count="13">wardenindoor</word><word count="13">games</word><word count="12">facilitiesuninterrupted</word><word count="12">power</word><word count="5">supplycontactprof.g.raghavaiah</word><word count="13">chief</word><word count="38">wardenphone</word><word count="38">no</word><word count="5">0891-2840480</word><word count="5">481dr.m.rama</word><word count="5">mohan</word><word count="15">rao</word><word count="5">0891-2840481dr.d.govinda</word><word count="20">non</word><word count="24">deputy</word><word count="5">7702966350dr.g.venkateswara</word><word count="5">0891-2840281dr.p.s.r.murthy</word><word count="5">0891-2840268dr.k.v.s.seshendra</word><word count="5">kumar</word><word count="1">0891-2840255santhi</word><word count="1">0891-2840255vinay</word><word count="1">0891-2840255rabindra</word><word count="1">sagar</word><word count="1">0891-2840255durgabai</word><word count="1">deshmukh</word><word count="1">0891-2840255</word><word count="3">girls</word><word count="2">kokila</word><word count="1">supplycontactprof.t.sita</word><word count="2">mahalakshmi</word><word count="8">warden</word><word count="2">0891-2840482</word><word count="1">559smt.n.vani</word><word count="1">9951958514</word><word count="1">0891-2840482prof.t.madhavi</word><word count="3">non-resident</word><word count="1">0891-2840482nirmala</word><word count="1">facilitiescontactprof.t.sita</word><word count="1">0891-2840482smt.</word><word count="1">m.d.jagadamba</word><word count="1">0891-2840559</word><word count="1">7396565515dr.anjali</word><word count="1">jha</word><word count="1">0891-2840559mrs.y.mallika</word><word count="4">blockhostel</word><word count="8">7.00</word><word count="4">8.45</word><word count="2">11.00</word><word count="2">2.30</word><word count="4">4.00</word><word count="4">supplycontactprof.a.sri</word><word count="4">ram</word><word count="1">9542424259b.s.r.k.prasad</word><word count="2">08455221213</word><word count="1">8985065793b</word><word count="1">9542424259b.s.r.k</word><word count="1">prasad</word><word count="1">8985065793</word><word count="1">p</word><word count="2">11.30</word><word count="2">1.30</word><word count="2">9542424259k.prabhavathi</word><word count="2">08455221222</word><word count="1">q</word><word count="1">vinay</word><word count="2">supplycontactdr.s.mastanamma</word><word count="1">wardendr.m.s.s.r.k.n.sarma</word><word count="1">wardensri</word><word count="1">m.v.brahmanada</word><word count="1">reddy</word><word count="1">wardendr.p.sharadha</word><word count="1">wardeng.manisha</word><word count="1">wardenwebmailcareerslibrarymapsalumniparentsdirectoryipinirf</word><word count="1">2017my.gitam</word><word count="1">admissionsevaluationacademics</word><word count="1">collaborationsplacementsprominent</word><word count="1">recruitersresultsin</word><word count="1">campusresearch</word><word count="1">university</word><word count="1">gandhinagar</word><word count="1">rushikonda</word><word count="1">visakhapatnam-45</word><word count="1">andhra</word><word count="1">pradesh</word><word count="1">indiamore</word><word count="1">details...</word><word count="1">2017</word><word count="1">all</word><word count="1">rights</word><word count="1">reserved</word></words></crawler>
